py_ufo_db/__init__.py
py_ufo_db/example.py
py_ufo_db/pyufodb.py
py_ufo_db-1.7.3.dist-info/LICENSE
py_ufo_db-1.7.3.dist-info/METADATA
py_ufo_db-1.7.3.dist-info/WHEEL
py_ufo_db-1.7.3.dist-info/top_level.txt
py_ufo_db-1.7.3.dist-info/RECORD
