Metadata-Version: 2.1
Name: py-ufo-db
Version: 1.7.3
Summary: Python Unified Flexible Object Database
Home-page: https://github.com/SL1dee36/pyufo-db
Author: @Sl1dee36, @Atxxxm
Author-email: spanishiwasc2@gmail.com
Classifier: Programming Language :: Python :: 3
Classifier: License :: OSI Approved :: MIT License
Classifier: Operating System :: OS Independent
Requires-Python: >=3.8
License-File: LICENSE
